setup.py
math_util/__init__.py
math_util/demo1.py
math_util/demo2.py
sxbwc.math_util.egg-info/PKG-INFO
sxbwc.math_util.egg-info/SOURCES.txt
sxbwc.math_util.egg-info/dependency_links.txt
sxbwc.math_util.egg-info/top_level.txt