Metadata-Version: 2.1
Name: sxbwc.math-util
Version: 1.0
Summary: 山西博微创数学计算工具包
Home-page: UNKNOWN
Author: rongweifeng
Author-email: 65489942@qq.com
License: UNKNOWN
Platform: UNKNOWN
